dailyrevenue/__init__.py
dailyrevenue/dailyrevenue.py
testingpackage-1.0.dist-info/METADATA
testingpackage-1.0.dist-info/WHEEL
testingpackage-1.0.dist-info/top_level.txt
testingpackage-1.0.dist-info/RECORD
